tui_dsmt/__init__.py
tui_dsmt/clustering/PAM.py
tui_dsmt/clustering/__init__.py
tui_dsmt/clustering/animation.py
tui_dsmt/clustering/datasets.py
tui_dsmt/clustering/draw.py
tui_dsmt/clustering/evaluation.py
tui_dsmt/clustering/hierarchical.py
tui_dsmt/clustering/interactive.py
tui_dsmt/clustering/tests.py
tui_dsmt/clustering/resources/ratio_voting.csv
tui_dsmt/fpm/BruteForceFI.py
tui_dsmt/fpm/ConditionalFPTree.py
tui_dsmt/fpm/ConditionalPatternBase.py
tui_dsmt/fpm/FPTree.py
tui_dsmt/fpm/HashTree.py
tui_dsmt/fpm/Itemset.py
tui_dsmt/fpm/ItemsetGrid.py
tui_dsmt/fpm/ItemsetGridApriori.py
tui_dsmt/fpm/ItemsetGridECLAT.py
tui_dsmt/fpm/NoneItemset.py
tui_dsmt/fpm/SequentialDatabase.py
tui_dsmt/fpm/SequentialItemset.py
tui_dsmt/fpm/TransactionDatabase.py
tui_dsmt/fpm/__init__.py
tui_dsmt/fpm/apriori.py
tui_dsmt/fpm/datasets.py
tui_dsmt/fpm/tests.py
tui_dsmt/fpm/resources/drinks.csv
tui_dsmt/fpm/resources/tweets_12_2020_25k.tsv
tui_dsmt/fpm/resources/website_tracking.csv
tui_dsmt/fpm/resources/website_tracking2.json
tui_dsmt/graph/BFS.py
tui_dsmt/graph/BipartiteFlow.py
tui_dsmt/graph/BronKerbosch.py
tui_dsmt/graph/COPRA.py
tui_dsmt/graph/DFS.py
tui_dsmt/graph/Dijkstra.py
tui_dsmt/graph/EdmondsKarp.py
tui_dsmt/graph/FordFulkerson.py
tui_dsmt/graph/FruchtermanReingold.py
tui_dsmt/graph/GirvanNewman.py
tui_dsmt/graph/Hall.py
tui_dsmt/graph/InteractiveGraph.py
tui_dsmt/graph/Kruskal.py
tui_dsmt/graph/LabelPropagation.py
tui_dsmt/graph/MarkovClusterAlgorithm.py
tui_dsmt/graph/MaximumFlow.py
tui_dsmt/graph/RandomWalk.py
tui_dsmt/graph/StoerWagner.py
tui_dsmt/graph/__init__.py
tui_dsmt/graph/datasets.py
tui_dsmt/graph/game.py
tui_dsmt/graph/html.py
tui_dsmt/graph/representation.py
tui_dsmt/graph/resources/bi_flow.csv
tui_dsmt/graph/resources/bi_small.csv
tui_dsmt/graph/resources/bipartite_exams.csv
tui_dsmt/graph/resources/bipartite_recommendations.csv
tui_dsmt/graph/resources/cliques_small.csv
tui_dsmt/graph/resources/community_small.csv
tui_dsmt-202509041045.dist-info/METADATA
tui_dsmt-202509041045.dist-info/WHEEL
tui_dsmt-202509041045.dist-info/top_level.txt
tui_dsmt-202509041045.dist-info/RECORD
