Metadata-Version: 2.4
Name: tui_dsmt
Version: 202509041045
Summary: everything you need for our jupyter notebooks
Home-page: https://dbgit.prakinf.tu-ilmenau.de/lectures/data-science-methoden-und-techniken
Author: Eric Tröbs
Author-email: eric.troebs@tu-ilmenau.de
Classifier: Programming Language :: Python :: 3
Classifier: License :: OSI Approved :: MIT License
Classifier: Operating System :: OS Independent
Requires-Python: >=3.10
Requires-Dist: jupyter
Requires-Dist: ipywidgets
Requires-Dist: checkmarkandcross
Requires-Dist: matplotlib~=3.10
Requires-Dist: networkx~=3.5
Requires-Dist: numpy~=2.3
Requires-Dist: plotly~=6.3
Requires-Dist: pandas~=2.3
Requires-Dist: scikit-learn~=1.7
Requires-Dist: ipyparallel~=9.0.0
Requires-Dist: ipython~=9.5.0
Requires-Dist: mlxtend~=0.23.0
Requires-Dist: mpi4py~=4.1.0
Requires-Dist: pyarrow~=21.0.0
Requires-Dist: pyfpgrowth~=1.0.0
Requires-Dist: pyspark~=4.0
Requires-Dist: fa2_modified==0.3.10
Dynamic: author
Dynamic: author-email
Dynamic: classifier
Dynamic: description
Dynamic: description-content-type
Dynamic: home-page
Dynamic: requires-dist
Dynamic: requires-python
Dynamic: summary
